fabricatio_memory-0.2.10.dist-info/METADATA
fabricatio_memory-0.2.10.dist-info/WHEEL
fabricatio_memory-0.2.10.dist-info/licenses/LICENSE
fabricatio_memory/__init__.py
fabricatio_memory/actions/__init__.py
fabricatio_memory/capabilities/__init__.py
fabricatio_memory/capabilities/remember.py
fabricatio_memory/capabilities/selective_remember.py
fabricatio_memory/config.py
fabricatio_memory/models/__init__.py
fabricatio_memory/models/note.py
fabricatio_memory/py.typed
fabricatio_memory/rust.cp313-win_amd64.pyd
fabricatio_memory/rust.pyi
fabricatio_memory/workflows/__init__.py
fabricatio_memory-0.2.10.dist-info/RECORD
