Metadata-Version: 2.4
Name: fabricatio-memory
Version: 0.2.10
Requires-Dist: fabricatio-core
Requires-Dist: fabricatio-judge ; extra == 'selective'
Provides-Extra: selective
License-File: LICENSE
Summary: An Extension of fabricatio aiming to extend the context llm could handle.
Author-email: Whth <zettainspector@foxmail.com>
Requires-Python: >=3.12, <3.15
Project-URL: Homepage, https://github.com/Whth/fabricatio
Project-URL: Repository, https://github.com/Whth/fabricatio
Project-URL: Issues, https://github.com/Whth/fabricatio/issues
